sicopa/__init__.py
sicopa-0.1.0.dist-info/LICENSE
sicopa-0.1.0.dist-info/METADATA
sicopa-0.1.0.dist-info/WHEEL
sicopa-0.1.0.dist-info/top_level.txt
sicopa-0.1.0.dist-info/RECORD
