Metadata-Version: 2.1
Name: sicopa
Version: 0.1.0
Summary: SImple COnfiguration PArser
Author-email: András Szalai <andrew@bandipapa.com>
License: Copyright (c) 2022, András Szalai
Project-URL: Homepage, https://github.com/bandipapa/sicopa
Requires-Python: >=3.8
License-File: LICENSE
